saturn_ml/fineTuning.py
saturn_ml/processData.py
saturn_ml-1.0.1.dist-info/LICENSE
saturn_ml-1.0.1.dist-info/METADATA
saturn_ml-1.0.1.dist-info/WHEEL
saturn_ml-1.0.1.dist-info/top_level.txt
saturn_ml-1.0.1.dist-info/RECORD
