Metadata-Version: 2.1
Name: saturn-ml
Version: 1.0.1
Summary: This will do your repetitive tasks in AI / ML projets 
Home-page: https://github.com/loriscience/SaTurN_ML
Author: Canberk Özkan
Author-email: canberk.ozkann@gmail.com
License: MIT
License-File: LICENSE
